questionnaire_core/__init__.py
questionnaire_core/admin.py
questionnaire_core/apps.py
questionnaire_core/fields.py
questionnaire_core/forms.py
questionnaire_core/settings.py
questionnaire_core/migrations/0001_initial.py
questionnaire_core/migrations/0002_auto_20210319_1650.py
questionnaire_core/migrations/__init__.py
questionnaire_core/models/__init__.py
questionnaire_core/models/questionnaire.py
questionnaire_core/models/result.py
questionnaire_core/question_types/__init__.py
questionnaire_core/question_types/base.py
questionnaire_core/question_types/boolean.py
questionnaire_core/question_types/choices.py
questionnaire_core/question_types/file_upload.py
questionnaire_core/question_types/multiple.py
questionnaire_core/question_types/number.py
questionnaire_core/question_types/range.py
questionnaire_core/question_types/text.py
questionnaire_core/templates/questionnaire_core/widgets/.gitkeep
questionnaire_core/views/__init__.py
questionnaire_core/views/generic.py
django_questionnaire_core-1.4.0.dist-info/LICENSE
django_questionnaire_core-1.4.0.dist-info/METADATA
django_questionnaire_core-1.4.0.dist-info/WHEEL
django_questionnaire_core-1.4.0.dist-info/top_level.txt
django_questionnaire_core-1.4.0.dist-info/RECORD
