Metadata-Version: 2.1
Name: django-questionnaire-core
Version: 1.4.0
Summary: A django application which can be used as a base for questionnaire functionality
Home-page: https://github.com/anfema/django-questionnaire-core
Author: anfema GmbH
Author-email: contact@anfe.ma
License: MIT
Classifier: Framework :: Django :: 3.2
Classifier: Framework :: Django :: 4.1
Classifier: Framework :: Django :: 4.2
Classifier: Programming Language :: Python :: 3
Classifier: Programming Language :: Python :: 3.8
Classifier: Programming Language :: Python :: 3.9
Classifier: Programming Language :: Python :: 3.10
Classifier: Programming Language :: Python :: 3.11
Classifier: License :: OSI Approved :: MIT License
Classifier: Operating System :: OS Independent
Requires-Python: >=3.8
License-File: LICENSE
Requires-Dist: django >=3.2
Requires-Dist: django-ordered-model
